{
  "title": "系统相关",
  "catelogs": [
    {
      "address": "https://medium.com/@imSamuel/%E5%B8%B8%E7%94%A8-apps-%E7%9A%84-url-schemes-%E6%95%B4%E7%90%86-380db3dff4d4#.256k2m3z4",
      "name": "常用 iOS Apps 的 URL Schemes 整理 — Medium",
      "favicon": "",
      "remark": ""
    },
    {
      "address": "http://blog.csdn.net/lwjok2007/article/details/47058795",
      "name": "iOS js oc相互调用（JavaScriptCore）（二） - - 博客频道 - CSDN.NET",
      "favicon": "",
      "remark": ""
    },
    {
      "address": "http://www.cocoachina.com/industry/20140514/8418.html",
      "name": "分析iOS Crash文件：符号化iOS Crash文件的3种方法 - CocoaChina 苹果开发中文站 - 最热的iPhone开发社区 最热的苹果开发社区 最热的iPad开发社区",
      "favicon": "",
      "remark": ""
    },
    {
      "address": "http://blog.csdn.net/u011056605/article/details/51584453",
      "name": "Xcode7.3工具解析App崩溃日志(.crash文件) - 博客频道 - CSDN.NET",
      "favicon": "",
      "remark": ""
    },
    {
      "address": "https://machinelearning.apple.com/",
      "name": "Apple Machine Learning Journal",
      "favicon": "",
      "remark": ""
    }
  ],
  "categories": []
}